json_repository/__init__.py
json_repository/context/__init__.py
json_repository/context/json_context.py
json_repository/errors/__init__.py
json_repository/errors/entity_not_found.py
json_repository/errors/more_than_one_result.py
json_repository/repositories/__init__.py
json_repository/repositories/base_json_repository.py
test/__init__.py
test/sample/__init__.py
test/sample/foobar_test.py
json_repository-0.2.2.dist-info/LICENSE
json_repository-0.2.2.dist-info/METADATA
json_repository-0.2.2.dist-info/WHEEL
json_repository-0.2.2.dist-info/top_level.txt
json_repository-0.2.2.dist-info/RECORD
