Metadata-Version: 2.1
Name: json-repository
Version: 0.2.2
Summary: A simple json repository
Home-page: https://github.com/mandrewcito/json_repository
Author: mandrewcito
Author-email: anbaalo@gmail.com
License: UNKNOWN
Keywords: json repository typed
Platform: UNKNOWN
Classifier: Programming Language :: Python :: 3
Classifier: Operating System :: OS Independent
